{
  "CengMianQuanZHong": 8,
  "CengMian": "人员管理",
  "Rules": [
    {
      "TestObject": "了解并遵守密码相关法律法规和密码管理制度",
      "ZhiBiaoYaoQiu": "8.6 a）相关人员应了解并遵守密码相关法律法规、密码应用安全管理制度；",
      "ZhiBiaoQuanZhong": 0.7
    },
    {
      "TestObject": "建立密码应用岗位责任制度",
      "ZhiBiaoYaoQiu": "8.6 b) 应建立密码应用岗位责任制度，明确各岗位在安全系统中的职责和权限：1) 根据密码应用的实际情况，设置密钥管理员、密码安全审计员、密码操作员等关键安全岗位；2) 对关键岗位建立多人共管机制；3) 密钥管理、密码安全审计、密码操作人员职责互相制约互相监督，其中密钥管理员岗位不可与密码审计员、密码操作员等关键安全岗位兼任；4) 相关设备与系统的管理和使用账号不得多人共用。",
      "ZhiBiaoQuanZhong": 1
    },
    {
      "TestObject": "建立上岗人员培训制度",
      "ZhiBiaoYaoQiu": "8.6 c) 应建立上岗人员培训制度，对于涉及密码的操作和管理的人员进行专门培训，确保其具备岗位所需专业技能；",
      "ZhiBiaoQuanZhong": 0.7
    },
    {
      "TestObject": "定期进行安全岗位人员考核",
      "ZhiBiaoYaoQiu": "8.6 d) 应定期对密码应用安全岗位人员进行考核；",
      "ZhiBiaoQuanZhong": 0.7
    },
    {
      "TestObject": "建立关键岗位人员保密制度和调离制度",
      "ZhiBiaoYaoQiu": "8.6 e) 应建立关键人员保密制度和调离制度，签订保密合同，承担保密义务。",
      "ZhiBiaoQuanZhong": 0.7
    }


  ]

}